icrawler/__init__.py
icrawler/crawler.py
icrawler/downloader.py
icrawler/feeder.py
icrawler/parser.py
icrawler/version.py
icrawler/builtin/__init__.py
icrawler/builtin/baidu.py
icrawler/builtin/bing.py
icrawler/builtin/filter.py
icrawler/builtin/flickr.py
icrawler/builtin/google.py
icrawler/builtin/greedy.py
icrawler/builtin/urllist.py
icrawler/storage/__init__.py
icrawler/storage/base.py
icrawler/storage/filesystem.py
icrawler/storage/google_storage.py
icrawler/utils/__init__.py
icrawler/utils/cached_queue.py
icrawler/utils/proxy_pool.py
icrawler/utils/session.py
icrawler/utils/signal.py
icrawler/utils/thread_pool.py
icrawler-0.6.9.dist-info/LICENSE
icrawler-0.6.9.dist-info/METADATA
icrawler-0.6.9.dist-info/WHEEL
icrawler-0.6.9.dist-info/top_level.txt
icrawler-0.6.9.dist-info/RECORD
