Metadata-Version: 2.1
Name: icrawler
Version: 0.6.9
Summary: A multi-thread crawler framework with many builtin image crawlers provided.
Author-email: Kai Chen <chenkaidev@gmail.com>, Zhiyuan Chen <this@zyc.ai>
Maintainer-email: Kai Chen <chenkaidev@gmail.com>, Zhiyuan Chen <this@zyc.ai>
License: The MIT License (MIT)
Project-URL: documentation, https://icrawler.readthedocs.io/
Project-URL: homepage, https://icrawler.readthedocs.io/
Project-URL: repository, https://github.com/hellock/icrawler
Keywords: Crawler
Classifier: Development Status :: 4 - Beta
Classifier: Intended Audience :: Developers
Classifier: Intended Audience :: Education
Classifier: Intended Audience :: Science/Research
Classifier: License :: OSI Approved :: MIT License
Classifier: Operating System :: OS Independent
Classifier: Programming Language :: Python :: 3 :: Only
Classifier: Programming Language :: Python :: 3.7
Classifier: Programming Language :: Python :: 3.8
Classifier: Programming Language :: Python :: 3.9
Classifier: Programming Language :: Python :: 3.10
Classifier: Programming Language :: Python :: 3.11
Classifier: Programming Language :: Python :: 3.12
Classifier: Topic :: Internet :: WWW/HTTP
Classifier: Topic :: Software Development :: Libraries :: Python Modules
Classifier: Topic :: Utilities
Requires-Python: >=3.7
License-File: LICENSE
Requires-Dist: beautifulsoup4
Requires-Dist: bs4
Requires-Dist: lxml
Requires-Dist: pillow
Requires-Dist: pyyaml
Requires-Dist: requests
Requires-Dist: six
